[
  {
    "author": [
      {
        "family": "Best",
        "given": "Further",
        "particle": "reading"
      },
      {
        "given": "Steven"
      },
      {
        "family": "Kellner",
        "given": "Douglas"
      }
    ],
    "date": [
      "1997"
    ],
    "location": [
      "New York and London"
    ],
    "publisher": [
      "Guilford Press"
    ],
    "title": [
      "The Postmodern Turn"
    ],
    "type": "book"
  },
  {
    "author": [
      {
        "family": "Connor",
        "given": "Steven"
      }
    ],
    "date": [
      "1989"
    ],
    "location": [
      "Oxford"
    ],
    "publisher": [
      "Blackwell"
    ],
    "title": [
      "Postmodernist Culture: An Introduction to Theories of the Contem­ porary"
    ],
    "type": "book"
  },
  {
    "author": [
      {
        "family": "Griffin",
        "given": "David Ray"
      },
      {
        "family": "Beardslee",
        "given": "William A."
      },
      {
        "family": "Holland",
        "given": "Joe"
      }
    ],
    "date": [
      "1989"
    ],
    "location": [
      "Albany"
    ],
    "publisher": [
      "State University of New York Press"
    ],
    "title": [
      "Varieties of Postmodern Theology"
    ],
    "type": "book"
  },
  {
    "author": [
      {
        "family": "Harvey",
        "given": "David"
      }
    ],
    "date": [
      "1990"
    ],
    "location": [
      "Oxford"
    ],
    "publisher": [
      "Blackwell"
    ],
    "title": [
      "The Condition of Postmodernity"
    ],
    "type": "book"
  },
  {
    "author": [
      {
        "family": "Hassan",
        "given": "Ihab"
      }
    ],
    "date": [
      "1987"
    ],
    "location": [
      "Columbus"
    ],
    "publisher": [
      "Ohio State University press"
    ],
    "title": [
      "The Postmodern Turn: Essays in Postmodern Theory and Culture"
    ],
    "type": "book"
  },
  {
    "author": [
      {
        "family": "Hyman",
        "given": "Gavin"
      }
    ],
    "date": [
      "2001"
    ],
    "location": [
      "Louisville"
    ],
    "publisher": [
      "Westminster/John Know"
    ],
    "title": [
      "The Predicament of Postmodern Theology: Radical Orthodoxy of Nihilist Textualism?"
    ],
    "type": "book"
  },
  {
    "date": [
      "1999"
    ],
    "editor": [
      {
        "family": "Kirk",
        "given": "J.Andrew"
      },
      {
        "family": "VanhoozeT",
        "given": "Kevin"
      }
    ],
    "location": [
      "Maryknoll, NY; Orbis"
    ],
    "title": [
      "To Stake a Claim: Mission and the Western Crisis of Knowledge"
    ],
    "type": null
  },
  {
    "author": [
      {
        "family": "Lakeland",
        "given": "Paul"
      }
    ],
    "date": [
      "1997"
    ],
    "location": [
      "Minneapolis"
    ],
    "publisher": [
      "Augsburg Fortress"
    ],
    "title": [
      "Postmodernity: Christian Identity in a Fragmented Age"
    ],
    "type": "book"
  },
  {
    "author": [
      {
        "family": "Lyotard",
        "given": "Jean-Francois"
      }
    ],
    "date": [
      "1984"
    ],
    "location": [
      "Manch­ ester"
    ],
    "publisher": [
      "Manchester University Press"
    ],
    "title": [
      "The Postmodern Condition: A Report on Knowledge"
    ],
    "type": "book"
  },
  {
    "author": [
      {
        "family": "Tilley",
        "given": "Terrence W."
      }
    ],
    "date": [
      "1995"
    ],
    "location": [
      "Maryknoll, NY"
    ],
    "publisher": [
      "Orbis"
    ],
    "title": [
      "Postmodern Theologies: The Challenge of Religious Diversity"
    ],
    "type": "book"
  },
  {
    "author": [
      {
        "family": "Ward",
        "given": "Graham"
      }
    ],
    "container-title": [
      "The Modem Theolo­ gians"
    ],
    "date": [
      "1997"
    ],
    "edition": [
      "2nd edn"
    ],
    "editor": [
      {
        "family": "Ford",
        "given": "David F."
      }
    ],
    "location": [
      "Oxford"
    ],
    "pages": [
      "585–601"
    ],
    "publisher": [
      "Blackwell"
    ],
    "title": [
      "Postmodern Theology"
    ],
    "type": "chapter"
  },
  {
    "author": [
      {
        "family": "Drury",
        "given": "M.O.'C."
      }
    ],
    "citation-number": [
      "3°"
    ],
    "container-title": [
      "Recollections of Wittgenstein"
    ],
    "date": [
      "1984"
    ],
    "editor": [
      {
        "family": "Rhees",
        "given": "Rush"
      }
    ],
    "location": [
      "Oxford"
    ],
    "pages": [
      "1 0 5"
    ],
    "publisher": [
      "Oxford University Press"
    ],
    "title": [
      "Some Notes on Conversations with Wittgenstein"
    ],
    "type": "chapter"
  },
  {
    "author": [
      {
        "family": "Kallenberg",
        "given": "Further",
        "particle": "reading"
      },
      {
        "family": "J",
        "given": "Brad"
      }
    ],
    "date": [
      "2001"
    ],
    "publisher": [
      "University of Notre Dame Press"
    ],
    "title": [
      "Ethics as Grammar: Changing the Postmodern Subject"
    ],
    "type": "book"
  },
  {
    "author": [
      {
        "family": "Kerr",
        "given": "Fergus"
      }
    ],
    "date": [
      "1986"
    ],
    "location": [
      "Oxford"
    ],
    "publisher": [
      "Blackwell"
    ],
    "title": [
      "Theology after Wittgenstein"
    ],
    "type": "book"
  },
  {
    "author": [
      {
        "family": "Lash",
        "given": "Nicholas"
      }
    ],
    "date": [
      "1986"
    ],
    "location": [
      "London"
    ],
    "publisher": [
      "SCM"
    ],
    "title": [
      "Theology on the Way to Emmaus"
    ],
    "type": "book"
  },
  {
    "author": [
      {
        "family": "Murphy",
        "given": "Nancey"
      }
    ],
    "date": [
      "1996"
    ],
    "location": [
      "Philadelphia"
    ],
    "publisher": [
      "Trinity Press International"
    ],
    "title": [
      "Beyond Liberalism and Fundamentalism"
    ],
    "type": "book"
  },
  {
    "author": [
      {
        "family": "Postmodernity",
        "given": "Anglo-American"
      }
    ],
    "date": [
      "1997"
    ],
    "location": [
      "Boulder, CO"
    ],
    "publisher": [
      "Westview Press"
    ],
    "title": [
      "Philosophical Perspectives on Science, Religion, and Ethics"
    ],
    "type": "book"
  },
  {
    "author": [
      {
        "family": "Placher",
        "given": "William C.-"
      }
    ],
    "date": [
      "1989"
    ],
    "location": [
      "Louisville, KY"
    ],
    "publisher": [
      "Westminster/John Knox Press"
    ],
    "title": [
      "Unapologetic Theology"
    ],
    "type": "book"
  },
  {
    "author": [
      {
        "family": "Rorty",
        "given": "Richard"
      }
    ],
    "date": [
      "1979",
      "1990"
    ],
    "location": [
      "Stephen, Cosmopolis"
    ],
    "publisher": [
      "Princeton University Press",
      "The Hidden Agenda of Modernity (University of Chicago Press"
    ],
    "title": [
      "Philosophy and the Mirror of Nature"
    ],
    "type": "book"
  },
  {
    "author": [
      {
        "family": "Wittgenstein",
        "given": "Ludwig"
      }
    ],
    "date": [
      "1958"
    ],
    "location": [
      "New York"
    ],
    "publisher": [
      "Macmillan"
    ],
    "title": [
      "Philosophical Investigations"
    ],
    "translator": [
      {
        "family": "Anscombe",
        "given": "G.E.M."
      }
    ],
    "type": "book"
  },
  {
    "author": [
      {
        "family": "Yoder",
        "given": "John Howard"
      }
    ],
    "edition": [
      "2nd edn"
    ],
    "note": [
      "Grand Rapids: Eerdmans, 1994). 3 Postliberal theology"
    ],
    "title": [
      "The Politics of Jesus"
    ],
    "type": null
  },
  {
    "author": [
      {
        "family": "Frei",
        "given": "Hans W."
      }
    ],
    "date": [
      "199a"
    ],
    "location": [
      "New Haven"
    ],
    "publisher": [
      "Yale University Press"
    ],
    "title": [
      "Types of Christian Theology"
    ],
    "type": "book"
  },
  {
    "author": [
      {
        "family": "Griffiths",
        "given": "Paul J."
      }
    ],
    "container-title": [
      "Anglican Theological Review"
    ],
    "date": [
      "1997"
    ],
    "pages": [
      "3–26"
    ],
    "title": [
      "The Properly Christian Response to Religious Plurality"
    ],
    "type": "article-journal",
    "volume": [
      "79"
    ]
  },
  {
    "author": [
      {
        "family": "Lindbeck",
        "given": "George"
      }
    ],
    "date": [
      "1985"
    ],
    "location": [
      "Philadelphia"
    ],
    "publisher": [
      "Westminster"
    ],
    "title": [
      "The Nature of Doctrine: Religion and Theology in a Postliberal Age"
    ],
    "type": "book"
  },
  {
    "author": [
      {
        "family": "Marshall",
        "given": "Bruce D."
      }
    ],
    "date": [
      "2000"
    ],
    "publisher": [
      "Cambridge University Press"
    ],
    "title": [
      "Trinity and Truth"
    ],
    "type": "book"
  },
  {
    "author": [
      {
        "family": "Deusen Hunsinger",
        "particle": "Van"
      },
      {
        "given": "Deborah"
      }
    ],
    "date": [
      "1995"
    ],
    "title": [
      "Theology and Pastoral Counseling (Grand Rapids: E e r d m a n s"
    ],
    "type": null
  },
  {
    "author": [
      {
        "family": "Watson",
        "given": "Francis"
      },
      {
        "family": "Text",
        "given": "Church"
      },
      {
        "given": "World"
      }
    ],
    "date": [
      "1994"
    ],
    "note": [
      "4 Postmetaphysical theology THOMAS A. CARLSON"
    ],
    "type": null
  },
  {
    "author": [
      {
        "family": "Caputo",
        "given": "Further",
        "particle": "reading"
      },
      {
        "family": "D",
        "given": "John"
      }
    ],
    "container-title": [
      "God, the Gift, and Postmod­ ernism"
    ],
    "date": [
      "1999"
    ],
    "editor": [
      {
        "given": "Caputo"
      },
      {
        "family": "Scanlon",
        "given": "Michael J."
      }
    ],
    "location": [
      "Bloomington"
    ],
    "publisher": [
      "Indiana University Press"
    ],
    "title": [
      "Apostles of the Impossible: On God and the Gift in Derrida and Marion"
    ],
    "type": "chapter"
  },
  {
    "author": [
      {
        "family": "Carlson",
        "given": "Thomas A."
      }
    ],
    "date": [
      "1999"
    ],
    "publisher": [
      "University of Chicago Press"
    ],
    "title": [
      "Indiscretion: Finitude and the Naming of God"
    ],
    "type": "book"
  },
  {
    "author": [
      {
        "family": "Derrida",
        "given": "Jacques"
      }
    ],
    "container-title": [
      "Derrida and Negative Theology"
    ],
    "date": [
      "1995",
      "1992"
    ],
    "editor": [
      {
        "literal": "ed."
      },
      {
        "family": "Coward",
        "given": "Harold"
      },
      {
        "family": "Foshay",
        "given": "Toby"
      }
    ],
    "location": [
      "Albany"
    ],
    "publisher": [
      "Thomas Dutoit (Stanford University Press",
      "State University of New York Press"
    ],
    "title": [
      "On the Name",
      "How to Avoid Speaking: Denials"
    ],
    "type": "chapter"
  },
  {
    "author": [
      {
        "family": "Heidegger",
        "given": "Martin"
      }
    ],
    "container-title": [
      "Identity and Difference",
      "The Piety of Thinking"
    ],
    "date": [
      "1969",
      "1976"
    ],
    "editor": [
      {
        "family": "Hart",
        "given": "James G."
      },
      {
        "family": "Maraldo",
        "given": "John C."
      }
    ],
    "location": [
      "New York",
      "Bloomington"
    ],
    "publisher": [
      "Harper and Row",
      "Indiana University Press"
    ],
    "title": [
      "The Onto-Theo-logical Constitution of Metaphysics",
      "Phenomenology and Theology"
    ],
    "translator": [
      {
        "family": "Stambaugh",
        "given": "Joan"
      }
    ],
    "type": "chapter"
  },
  {
    "author": [
      {
        "family": "Marion",
        "given": "Jean-Luc"
      },
      {
        "family": "Carlson",
        "given": "Philosophy Today"
      }
    ],
    "container-title": [
      "The Cambridge History of Seventeenth-Century Philos­ ophy",
      "Critical Inquiry"
    ],
    "date": [
      "1991",
      "1993",
      "1994"
    ],
    "editor": [
      {
        "family": "Garber",
        "given": "Daniel"
      },
      {
        "family": "Ayers",
        "given": "Michael"
      }
    ],
    "note": [
      "Cambridge University Press, 1998)."
    ],
    "pages": [
      "103–24",
      "572–91"
    ],
    "publisher": [
      "University of Chicago Press"
    ],
    "title": [
      "God without Being",
      "The Saturated Phenomenon",
      "Metaphysics and Phenomenology: A Relief for Theology",
      "The Idea of God"
    ],
    "translator": [
      {
        "family": "Carlson",
        "given": "Thomas A."
      },
      {
        "family": "Thomas",
        "given": "A."
      },
      {
        "family": "Carlson",
        "given": "Thomas A."
      },
      {
        "family": "Carlson",
        "given": "Thomas A."
      },
      {
        "family": "Garber",
        "given": "Daniel"
      }
    ],
    "type": "article-journal",
    "volume": [
      "20",
      "1"
    ]
  },
  {
    "date": [
      "1997"
    ],
    "location": [
      "Bloomington",
      "1997)-(Louisville"
    ],
    "publisher": [
      "Indiana University Press",
      "Westminster |ohn Knox Press"
    ],
    "type": "book"
  },
  {
    "author": [
      {
        "family": "Milbank",
        "given": "See"
      }
    ],
    "date": [
      "1990",
      "1997"
    ],
    "location": [
      "Oxford",
      "Oxford"
    ],
    "note": [
      "84 Graham Ward"
    ],
    "publisher": [
      "Blackwell",
      "Blackwell"
    ],
    "title": [
      "Theology and Social Theory",
      "and Pickstock, After Writing: The Liturgical Consummation of Philosophy"
    ],
    "type": null
  },
  {
    "author": [
      {
        "family": "Caputo",
        "given": "Further",
        "particle": "reading"
      },
      {
        "family": "D",
        "given": "John"
      }
    ],
    "date": [
      "1997"
    ],
    "location": [
      "Bloomington"
    ],
    "publisher": [
      "Indiana University Press"
    ],
    "title": [
      "The Prayers and Tears of Jacques Derrida"
    ],
    "type": "book"
  },
  {
    "author": [
      {
        "family": "Hart",
        "given": "Kevin"
      }
    ],
    "date": [
      "1989"
    ],
    "publisher": [
      "Cambridge University Press"
    ],
    "title": [
      "The Trespass of the Sign: Deconstruction, Theology and Philosophy"
    ],
    "type": "book"
  },
  {
    "author": [
      {
        "family": "Lowe",
        "given": "Walter"
      }
    ],
    "date": [
      "1993"
    ],
    "location": [
      "Bloomington"
    ],
    "publisher": [
      "Indiana University Press"
    ],
    "title": [
      "Theology and Difference: The Wound of Reason"
    ],
    "type": "book"
  },
  {
    "author": [
      {
        "family": "Ward",
        "given": "Graham"
      },
      {
        "given": "Barth"
      }
    ],
    "date": [
      "1995"
    ],
    "publisher": [
      "Cambridge University Press"
    ],
    "title": [
      "Derrida and the Language of Theology"
    ],
    "type": "book"
  },
  {
    "container-title": [
      "Trinity in Process: A Rela tional Theology of God"
    ],
    "date": [
      "1997"
    ],
    "editor": [
      {
        "family": "Bracken",
        "given": "Further",
        "particle": "reading"
      }
    ],
    "location": [
      "New York"
    ],
    "publisher": [
      "Continuum"
    ],
    "type": "chapter"
  },
  {
    "author": [
      {
        "family": "Cobb",
        "given": "John B.",
        "suffix": "Jr"
      }
    ],
    "date": [
      "1975"
    ],
    "location": [
      "Philadelphia"
    ],
    "publisher": [
      "Westminster"
    ],
    "title": [
      "Christ in a Pluralistic Age"
    ],
    "type": "book"
  },
  {
    "author": [
      {
        "family": "Griffin",
        "given": "David Ray"
      }
    ],
    "date": [
      "1988"
    ],
    "publisher": [
      "State University of New York Press"
    ],
    "title": [
      "God and Religion in the Postmodern World"
    ],
    "type": "book"
  },
  {
    "date": [
      "2002"
    ],
    "editor": [
      {
        "family": "Keller",
        "given": "Catherine"
      },
      {
        "family": "Daniell",
        "given": "Anne"
      }
    ],
    "location": [
      "Albany"
    ],
    "publisher": [
      "State University of New York Press"
    ],
    "title": [
      "Process and Difference: Between Cosmological and Poststructuralist Postmodemisms"
    ],
    "type": "book"
  },
  {
    "author": [
      {
        "family": "Whitehead",
        "given": "Alfred North"
      }
    ],
    "date": [
      "1978"
    ],
    "edition": [
      "corr. edn"
    ],
    "editor": [
      {
        "family": "David Ray Griffin",
        "particle": "eds."
      },
      {
        "family": "Sherburne",
        "given": "Donald W."
      }
    ],
    "location": [
      "New York"
    ],
    "publisher": [
      "Free Press"
    ],
    "title": [
      "Process and Reality: an Essay in Cosmology"
    ],
    "type": "book"
  },
  {
    "author": [
      {
        "family": "Althaus-Reid",
        "given": "Marcella"
      }
    ],
    "date": [
      "2002"
    ],
    "location": [
      "New York"
    ],
    "note": [
      "Feminist theology 123"
    ],
    "publisher": [
      "Routledge"
    ],
    "title": [
      "Indecent Theology: Theological Per/versions in Sex, Gender and Politics"
    ],
    "type": null
  },
  {
    "author": [
      {
        "family": "Armour",
        "given": "Further",
        "particle": "reading"
      },
      {
        "given": "Ellen"
      }
    ],
    "container-title": [
      "Transfigurations: Theology and the French Feminists (Minneapo"
    ],
    "date": [
      "1993"
    ],
    "editor": [
      {
        "family": "Kim",
        "given": "C.W.Maggie"
      },
      {
        "family": "Ville",
        "given": "Susan M.",
        "particle": "St."
      },
      {
        "family": "Simonaitis",
        "given": "Susan M."
      },
      {
        "given": "eds"
      }
    ],
    "location": [
      "lis"
    ],
    "pages": [
      "143–69"
    ],
    "publisher": [
      "Fortress Press"
    ],
    "title": [
      "Questioning 'Woman' in Feminist/Wornanist Theology: Irigaray, Ruether, and Daly"
    ],
    "type": "chapter"
  },
  {
    "container-title": [
      "Horizons in Feminist Theology: Identity, Tradition, and Norms"
    ],
    "date": [
      "1997"
    ],
    "editor": [
      {
        "family": "Chopp",
        "given": "Rebecca"
      },
      {
        "family": "Davaney",
        "given": "Sheila Greeve"
      }
    ],
    "location": [
      "Minneapolis"
    ],
    "publisher": [
      "Fortress Press"
    ],
    "type": "chapter"
  },
  {
    "author": [
      {
        "family": "Kim",
        "given": "C.W.Maggie"
      },
      {
        "family": "Ville",
        "given": "Susan M.",
        "particle": "St."
      },
      {
        "family": "M",
        "given": "Susan"
      }
    ],
    "container-title": [
      "Transfigura­ tions: Theology and the French Feminists"
    ],
    "date": [
      "1993"
    ],
    "editor": [
      {
        "literal": "eds."
      }
    ],
    "location": [
      "Minneapolis"
    ],
    "publisher": [
      "Fortress Press"
    ],
    "title": [
      "Simonaitis"
    ],
    "type": "chapter"
  },
  {
    "author": [
      {
        "literal": "Haraway, Donna,\""
      }
    ],
    "container-title": [
      "Simians, Cyborgs, and Women: The Reinvention of Nature"
    ],
    "date": [
      "1991"
    ],
    "location": [
      "New York"
    ],
    "pages": [
      "127–48"
    ],
    "publisher": [
      "Routledge"
    ],
    "title": [
      "'Gender' for a Marxist Dictionary: The Sexual Politics of a Word"
    ],
    "type": "chapter"
  },
  {
    "container-title": [
      "Judaism Since Gender"
    ],
    "date": [
      "1997"
    ],
    "editor": [
      {
        "family": "Peskowitz",
        "given": "Miriam"
      },
      {
        "family": "Levitt",
        "given": "Laura"
      }
    ],
    "location": [
      "New York"
    ],
    "publisher": [
      "Routledge"
    ],
    "type": "chapter"
  },
  {
    "author": [
      {
        "family": "Tolbert",
        "given": "Mary Ann"
      }
    ],
    "container-title": [
      "Handbook of Postmodern Biblical Interpretation (St"
    ],
    "date": [
      "2000"
    ],
    "editor": [
      {
        "family": "Adam",
        "given": "A.K.M."
      }
    ],
    "location": [
      "Louis"
    ],
    "pages": [
      "99–105"
    ],
    "publisher": [
      "Chalice Press"
    ],
    "title": [
      "Gender"
    ],
    "type": "chapter"
  },
  {
    "author": [
      {
        "family": "Weigman",
        "given": "Robyn"
      }
    ],
    "date": [
      "1995"
    ],
    "location": [
      "Durham, NC"
    ],
    "publisher": [
      "Duke University Press"
    ],
    "title": [
      "American Anatomies: Theorizing Race and Gender"
    ],
    "type": "book"
  },
  {
    "author": [
      {
        "family": "Adam",
        "given": "A.K.M.",
        "particle": "Further reading"
      }
    ],
    "date": [
      "1995"
    ],
    "location": [
      "Minneapolis"
    ],
    "publisher": [
      "Augsburg Fortress"
    ],
    "title": [
      "What is Postmodern Biblical Criticism?"
    ],
    "type": "book"
  },
  {
    "date": [
      "2001"
    ],
    "editor": [
      {
        "family": "Buckley",
        "given": "James J."
      },
      {
        "family": "Yeago",
        "given": "David S."
      }
    ],
    "location": [
      "Grand Rapids"
    ],
    "pages": [
      "49–93"
    ],
    "publisher": [
      "Eerdmans"
    ],
    "title": [
      "Knowing the Triune Cod: The Work of the Spirit in the Practices of the Church"
    ],
    "type": "book"
  },
  {
    "container-title": [
      "The Postmodern Bible (New Haven and"
    ],
    "date": [
      "1995"
    ],
    "editor": [
      {
        "family": "CastelH",
        "given": "Elizabeth A."
      },
      {
        "family": "Moore",
        "given": "Stephen D."
      },
      {
        "family": "Phillips",
        "given": "Gary A."
      },
      {
        "family": "Schwartz",
        "given": "Regina M."
      },
      {
        "given": "eds"
      }
    ],
    "location": [
      "London"
    ],
    "publisher": [
      "Yale Univer­ sity Press"
    ],
    "type": "chapter"
  },
  {
    "author": [
      {
        "family": "Hens-Piazza",
        "given": "Gina"
      }
    ],
    "date": [
      "2002"
    ],
    "location": [
      "Minneapolis"
    ],
    "publisher": [
      "Augsburg Fortress"
    ],
    "title": [
      "The New Historicism"
    ],
    "type": "book"
  },
  {
    "author": [
      {
        "family": "Hiitter",
        "given": "Reinhard"
      }
    ],
    "date": [
      "2000"
    ],
    "location": [
      "Grand Rapids"
    ],
    "publisher": [
      "Eerdmans"
    ],
    "title": [
      "Suffering Divine Things: Theology as Church Practice"
    ],
    "type": "book"
  },
  {
    "author": [
      {
        "family": "Vanhoozer",
        "given": "Kevin J."
      }
    ],
    "date": [
      "forthcoming"
    ],
    "location": [
      "Louisville, KY"
    ],
    "publisher": [
      "Westminster/John Knox"
    ],
    "title": [
      "The Drama of Doctrine: A Canonical-Linguistic Approach to Theology"
    ],
    "type": "book"
  },
  {
    "author": [
      {
        "family": "Webster",
        "given": "John"
      }
    ],
    "date": [
      "2001"
    ],
    "location": [
      "Edinburgh and New York"
    ],
    "publisher": [
      "T. & T. Clark"
    ],
    "title": [
      "Word and Church"
    ],
    "type": "book"
  },
  {
    "author": [
      {
        "family": "Williams",
        "given": "D.H."
      }
    ],
    "date": [
      "1999"
    ],
    "location": [
      "Grand Rapids"
    ],
    "publisher": [
      "Eerdmans"
    ],
    "title": [
      "Retrieving the Tradition and Renewing Evangelicalism: A Primer for Suspicious Protestants"
    ],
    "type": "book"
  },
  {
    "author": [
      {
        "family": "Wolterstorff",
        "given": "Nicholas"
      }
    ],
    "date": [
      "1995"
    ],
    "note": [
      "io Theological method"
    ],
    "publisher": [
      "Cambridge University Press"
    ],
    "title": [
      "Divine Discourse: Philosophical Reflections on the Claim that God Speaks"
    ],
    "type": null
  },
  {
    "author": [
      {
        "family": "McClendon",
        "particle": "James W m.",
        "suffix": "Jr"
      }
    ],
    "container-title": [
      "Doctrine: Systematic Theology",
      "Witness: Systematic Theology"
    ],
    "date": [
      "1986",
      "1994",
      "2000"
    ],
    "location": [
      "Nashville",
      "Nashville",
      "Nashville; Abingdon"
    ],
    "publisher": [
      "Abingdon Press",
      "Abingdon Press"
    ],
    "title": [
      "Ethics: Systematic Theology"
    ],
    "type": "article-journal",
    "volume": [
      "1",
      "2",
      "3"
    ]
  },
  {
    "date": [
      "1991"
    ],
    "editor": [
      {
        "family": "Augustine",
        "given": "The Trinity"
      },
      {
        "family": "Edmund Hill",
        "particle": "ed."
      }
    ],
    "location": [
      "Brooklyn, NY"
    ],
    "publisher": [
      "New City Press"
    ],
    "type": "book"
  },
  {
    "author": [
      {
        "family": "Boff",
        "given": "Leonardo"
      }
    ],
    "date": [
      "1988"
    ],
    "location": [
      "Maryknoll, NY"
    ],
    "publisher": [
      "Orbis Books"
    ],
    "title": [
      "Trinity and Society"
    ],
    "translator": [
      {
        "family": "Burns",
        "given": "Paul"
      }
    ],
    "type": "book"
  },
  {
    "author": [
      {
        "family": "Cunningham",
        "given": "David S."
      }
    ],
    "date": [
      "1998"
    ],
    "location": [
      "Oxford"
    ],
    "publisher": [
      "Blackwell"
    ],
    "title": [
      "These Three Are One: The Practice of Trinitarian Theology"
    ],
    "type": "book"
  },
  {
    "author": [
      {
        "family": "Johnson",
        "given": "Elizabeth A."
      },
      {
        "family": "LaCugna",
        "given": "David S.Cunningham"
      },
      {
        "family": "Mowry",
        "given": "Catherine"
      }
    ],
    "date": [
      "1992",
      "1991"
    ],
    "location": [
      "New York",
      "San Francisco"
    ],
    "note": [
      "Creed (University of Notre Dame Press, 1992)."
    ],
    "pages": [
      "202"
    ],
    "publisher": [
      "Crossroad",
      "HarperCollins"
    ],
    "title": [
      "She Who Is: The Mystery of God in Feminist Theological Discourse",
      "Goof For Us: The Trinity and Christian Life",
      "Nicholas, Believing Three Ways In One God: A Reading of the Apostles'"
    ],
    "type": null
  },
  {
    "author": [
      {
        "family": "Marshall",
        "given": "Bruce D."
      }
    ],
    "date": [
      "2000"
    ],
    "publisher": [
      "Cambridge University Press"
    ],
    "title": [
      "Trinity and Truth"
    ],
    "type": "book"
  },
  {
    "author": [
      {
        "family": "Milbank",
        "given": "John"
      }
    ],
    "container-title": [
      "Faith Gives Fullness to Reasoning: The Five Theological Orations of Gregory Nazianzen",
      "Modern Theology",
      "Modem Theology"
    ],
    "date": [
      "1986",
      "1995",
      "1991"
    ],
    "editor": [
      {
        "literal": "i -Norris, Frederick W., ed."
      }
    ],
    "location": [
      "Leiden"
    ],
    "pages": [
      "213–34"
    ],
    "publisher": [
      "E. J. Brill"
    ],
    "title": [
      "The Second Difference: Toward a Trinitarianism Without Reserve",
      "Can a Gift be Given ? Prolegomena to a Trinitarian Metaphysics"
    ],
    "translator": [
      {
        "family": "Wickham",
        "given": "Lionel"
      },
      {
        "family": "Williams",
        "given": "Frederick"
      }
    ],
    "type": "article-journal",
    "volume": [
      "2",
      "6 11",
      "i i 9"
    ]
  },
  {
    "author": [
      {
        "family": "Rogers",
        "given": "Eugene R.",
        "suffix": "Jr"
      }
    ],
    "date": [
      "1999"
    ],
    "location": [
      "Oxford"
    ],
    "publisher": [
      "Blackweil"
    ],
    "title": [
      "Sexuality and the Christian Body: Their Way Into the Triune God"
    ],
    "type": "book"
  },
  {
    "author": [
      {
        "family": "Volf",
        "given": "Miroslav"
      }
    ],
    "date": [
      "1998"
    ],
    "location": [
      "Grand Rapids"
    ],
    "publisher": [
      "Eerdmans"
    ],
    "title": [
      "After Our Likeness: The Church as the Image of the Trinity"
    ],
    "type": "book"
  },
  {
    "author": [
      {
        "family": "Robert",
        "given": "N."
      },
      {
        "given": "Bellah"
      }
    ],
    "container-title": [
      "The Essential Communitarian Reader"
    ],
    "pages": [
      "1"
    ],
    "title": [
      "Community Properly Understood: A Defense of 'Democratic Communitarianism,\"'"
    ],
    "type": "chapter",
    "volume": [
      "6"
    ]
  },
  {
    "author": [
      {
        "family": "point",
        "given": "On",
        "particle": "this"
      },
      {
        "family": "also",
        "particle": "see"
      },
      {
        "family": "Bellah",
        "given": "Robert N."
      },
      {
        "family": "Madsen",
        "given": "Richard"
      },
      {
        "family": "Sullivan",
        "given": "William M."
      },
      {
        "others": true
      }
    ],
    "container-title": [
      "Individualism and Commitment in American Life, Perennial Library edition"
    ],
    "date": [
      "1986"
    ],
    "location": [
      "New York"
    ],
    "pages": [
      ", 8 1"
    ],
    "publisher": [
      "Harper & Row"
    ],
    "title": [
      "Habits of the Heart"
    ],
    "type": "chapter"
  },
  {
    "author": [
      {
        "family": "Nisbet",
        "given": "Robert"
      },
      {
        "family": "Perrin",
        "given": "Robert G."
      }
    ],
    "edition": [
      "2nd edn"
    ],
    "location": [
      "New York"
    ],
    "pages": [
      "100"
    ],
    "publisher": [
      "Alfred A. Knopf"
    ],
    "title": [
      "The Social Bond"
    ],
    "type": "book",
    "volume": [
      "1 9 7 7"
    ]
  },
  {
    "author": [
      {
        "family": "Nisbet",
        "given": "Robert A."
      }
    ],
    "date": [
      "1966"
    ],
    "location": [
      "New York"
    ],
    "pages": [
      "48"
    ],
    "publisher": [
      "Basic Books"
    ],
    "title": [
      "The Sociological Tradition"
    ],
    "type": "book"
  },
  {
    "author": [
      {
        "family": "McClendon",
        "given": "William",
        "particle": "fames",
        "suffix": "Jr"
      }
    ],
    "date": [
      "1986"
    ],
    "issue": [
      "ville, T N "
    ],
    "location": [
      "Abingdon"
    ],
    "pages": [
      "2 8"
    ],
    "title": [
      "Ethics: Systematic Theology"
    ],
    "type": null,
    "volume": []
  },
  {
    "author": [
      {
        "family": "Milbank",
        "given": "John"
      }
    ],
    "date": [
      "1990"
    ],
    "location": [
      "Oxford"
    ],
    "pages": [
      "380",
      "259"
    ],
    "publisher": [
      "Blackwell",
      "Ecclesiology"
    ],
    "title": [
      "Theology and Social Theory: Beyond Secular Reason"
    ],
    "type": "book"
  },
  {
    "author": [
      {
        "family": "Fergusson",
        "given": "David"
      },
      {
        "given": "Community"
      }
    ],
    "date": [
      "1998"
    ],
    "note": [
      "1 5 7 . 26o Stanley ). Grenz"
    ],
    "pages": [],
    "publisher": [
      "Cambridge University Press"
    ],
    "title": [
      "Liberalism and Christian Ethics"
    ],
    "type": null
  },
  {
    "author": [
      {
        "family": "Avis",
        "given": "Paul D.L."
      }
    ],
    "location": [
      "Atlanta"
    ],
    "pages": [
      "8"
    ],
    "publisher": [
      "John Knox"
    ],
    "title": [
      "The Church in the Theology of the Reformers"
    ],
    "type": "book",
    "volume": [
      "1 9 8 1"
    ]
  },
  {
    "author": [
      {
        "family": "Grenz",
        "given": "Further",
        "particle": "reading"
      },
      {
        "given": "Stanley"
      }
    ],
    "date": [
      "2000",
      "1981"
    ],
    "location": [
      "Grand Rapids"
    ],
    "publisher": [
      "Eerdmans",
      "University of Notre Dame Press"
    ],
    "title": [
      "Theology for the Community ofGod",
      "Hauerwas, Stanley, A Community of Character: Toward a Constructive Christian Social Ethic"
    ],
    "type": "book"
  },
  {
    "author": [
      {
        "given": "Moltmann"
      }
    ],
    "date": [
      "1993",
      "2000"
    ],
    "location": [
      "Minneapolis",
      "Grand Rapids"
    ],
    "publisher": [
      "Fortress",
      "Baker"
    ],
    "title": [
      "The Church in the Power of the Spirit: A Contribution to Messianic Ecclesiology",
      "Van Gelder, Craig, The Essence of the Church: A Community Created by the Spirit"
    ],
    "type": "book"
  },
  {
    "author": [
      {
        "family": "Volf",
        "given": "Miroslav"
      }
    ],
    "date": [
      "1998"
    ],
    "location": [
      "Grand Rapids"
    ],
    "publisher": [
      "Eerdmans"
    ],
    "title": [
      "After Our Likeness: The Church as the Image of the Trinity"
    ],
    "type": "book"
  },
  {
    "author": [
      {
        "family": "Wyschogrod",
        "given": "Edith"
      },
      {
        "family": "Ashes. Hegel",
        "given": "Spirit",
        "particle": "in"
      },
      {
        "given": "Heidegger"
      },
      {
        "family": "Death",
        "given": "Man-Made Mass"
      }
    ],
    "container-title": [
      "Interpreting Judaism in a Postmodern Age"
    ],
    "date": [
      "1996"
    ],
    "editor": [
      {
        "family": "Kepnes",
        "given": "Steven"
      }
    ],
    "location": [
      "New York and London"
    ],
    "note": [
      "3 0 1 - 2 1 -9 Dietrich Bonhoeffer Werke (Munich: Christian Kaiser Verlag, 1 9 8 6 - 1 9 9 9 ) ."
    ],
    "pages": [
      "273"
    ],
    "publisher": [
      "New York University Press",
      "Holy Spirit and Christian spirituality"
    ],
    "title": [
      "YaJe University Press, 1 9 8 5 ) . Cf. her linking of the Holocaust with postmodern Jewish thought in \"Hasidism, Hellenism, Holocaust"
    ],
    "type": "chapter"
  },
  {
    "author": [
      {
        "family": "D",
        "given": "Cf Paul"
      }
    ],
    "date": [
      "2000"
    ],
    "genre": [
      "{Ph.D. Dissertation,"
    ],
    "note": [
      "unpublished)."
    ],
    "publisher": [
      "Cambridge University"
    ],
    "title": [
      "Redeeming Modernity. Rationality, Justification, and Penultimacy in the Theology of Dietrich Bonhoeffer"
    ],
    "type": "thesis"
  }
]
