[
  {
    "author": [
      {
        "family": "Tu",
        "given": "Runsheng"
      }
    ],
    "citation-number": [
      "1"
    ],
    "date": [
      "2015"
    ],
    "location": [
      "Lanham"
    ],
    "publisher": [
      "American Academic Press"
    ],
    "title": [
      "Local Realism Quantum Mechanics, 1-242"
    ],
    "type": "book"
  },
  {
    "author": [
      {
        "family": "Aharonov",
        "given": "Y."
      },
      {
        "family": "Albert",
        "given": "D.Z."
      },
      {
        "family": "Vaidman",
        "given": "L."
      }
    ],
    "citation-number": [
      "2"
    ],
    "container-title": [
      "Phys. Rev. Letts"
    ],
    "date": [
      "1988"
    ],
    "pages": [
      "1351"
    ],
    "type": "article-journal",
    "volume": [
      "60"
    ]
  },
  {
    "author": [
      {
        "family": "Turck",
        "given": "Yusuf"
      }
    ],
    "citation-number": [
      "3"
    ],
    "date": [
      "2012"
    ],
    "publisher": [
      "Graduate University of Chinese Academy of Sciences"
    ],
    "title": [
      "Quantum Weak Measurement Theory and Its Applications [D"
    ],
    "type": "book"
  },
  {
    "author": [
      {
        "family": "Rozema",
        "given": "Lee A."
      },
      {
        "family": "Darabi",
        "given": "Ardavan"
      },
      {
        "family": "Mahler",
        "given": "Dylan H."
      },
      {
        "family": "Hayat",
        "given": "Alex"
      },
      {
        "family": "Soudagar",
        "given": "Yasaman"
      },
      {
        "family": "Steinberg",
        "given": "Aephraim M."
      }
    ],
    "citation-number": [
      "4"
    ],
    "container-title": [
      "Phys. Rev. Lett"
    ],
    "date": [
      "2012"
    ],
    "pages": [
      "100404"
    ],
    "title": [
      "Violation of Heisenberg’s Measurement-Disturbance Relationship by Weak Measurements"
    ],
    "type": "article-journal",
    "volume": [
      "109"
    ]
  },
  {
    "author": [
      {
        "family": "Kocsis",
        "given": "S."
      },
      {
        "family": "Steinberg",
        "given": "A.M."
      },
      {
        "others": true
      }
    ],
    "citation-number": [
      "5"
    ],
    "container-title": [
      "Science"
    ],
    "date": [
      "2011",
      "1170"
    ],
    "title": [
      "Observing the Average Trajectories of Single Photons in a Two-slit Interferometer",
      "An experiment which determined the Trajectories of Quantum Inverse Measurement Theory Supports the Interpretation 93 of Localized Realism and Determinism Single Photons through a Two-slit Interferometer"
    ],
    "type": "article-journal",
    "volume": [
      "332"
    ]
  },
  {
    "author": [
      {
        "family": "Einstein",
        "given": "A."
      }
    ],
    "citation-number": [
      "6"
    ],
    "container-title": [
      "Journal of the Franklin Institute"
    ],
    "date": [
      "1936"
    ],
    "note": [
      "reprinted in translation in Einstein (1954)."
    ],
    "pages": [
      "313–347,"
    ],
    "title": [
      "Physik und Realität"
    ],
    "type": "article-journal",
    "volume": [
      "221"
    ]
  },
  {
    "author": [
      {
        "family": "Einstein",
        "given": "A."
      },
      {
        "family": "Podolsky",
        "given": "B."
      },
      {
        "family": "Rosen",
        "given": "N."
      }
    ],
    "citation-number": [
      "7"
    ],
    "container-title": [
      "Physical Review"
    ],
    "date": [
      "1935"
    ],
    "pages": [
      "777–780",
      "–"
    ],
    "title": [
      "Can Quantum-Mechanical Description of Physical Reality Be Considered Complete?"
    ],
    "type": "article-journal",
    "url": [
      "http://fanyi.baidu.com/"
    ],
    "volume": [
      "47"
    ]
  },
  {
    "author": [
      {
        "family": "Weinberg",
        "given": "Steven"
      }
    ],
    "citation-number": [
      "8"
    ],
    "date": [
      "2017"
    ],
    "title": [
      "The Trouble with Quantum Mechanics"
    ],
    "type": null
  },
  {
    "container-title": [
      "The New York Review of Books"
    ],
    "date": [
      "2017-01-19"
    ],
    "note": [
      "Issue."
    ],
    "type": "article-journal"
  },
  {
    "type": null,
    "url": [
      "http://www.nybooks.com/articles/2017/01/19/trouble-with-quantum"
    ]
  },
  {
    "author": [
      {
        "family": "Tu",
        "given": "Runsheng"
      }
    ],
    "citation-number": [
      "9"
    ],
    "date": [
      "2015"
    ],
    "location": [
      "Lanham"
    ],
    "publisher": [
      "American Academic Press"
    ],
    "title": [
      "Local Realism Quantum Mechanics, 1-242"
    ],
    "type": "book"
  },
  {
    "author": [
      {
        "family": "Shi",
        "given": "Yu"
      }
    ],
    "citation-number": [
      "10"
    ],
    "container-title": [
      "Guangming Daily"
    ],
    "date": [
      "2017",
      "2017-05-25"
    ],
    "edition": [
      "13th"
    ],
    "title": [
      "Continue the quantum mechanics revolution"
    ],
    "type": "article-journal"
  },
  {
    "author": [
      {
        "family": "Tu",
        "given": "Runsheng"
      }
    ],
    "citation-number": [
      "11"
    ],
    "container-title": [
      "Infinite Energy"
    ],
    "date": [
      "2013"
    ],
    "issue": [
      "107"
    ],
    "pages": [
      "44–46"
    ],
    "title": [
      "The Formula Whose Shape Is Similar to a Heisenberg Relation Possesses the Double Meanings of Determinism and Indeterminism"
    ],
    "type": "article-journal",
    "url": [
      "http://www.docin.com/p-765650007.html."
    ],
    "volume": []
  },
  {
    "author": [
      {
        "family": "Bohr",
        "given": "N."
      }
    ],
    "citation-number": [
      "12"
    ],
    "date": [
      "1929",
      "1929"
    ],
    "note": [
      "Naturwissenschaften, Planck special issue. Originally published in German in Naturwissenschaft,",
      "First published in English in 1934 by Cambridge University Press."
    ],
    "title": [
      "The Quantum of Action and the Description of Nature"
    ],
    "type": null,
    "volume": [
      "17"
    ]
  },
  {
    "author": [
      {
        "family": "Rae",
        "given": "Alastair"
      }
    ],
    "citation-number": [
      "13"
    ],
    "container-title": [
      "J. J. Sakurai, Modern Quantum Mechanics"
    ],
    "date": [
      "1991"
    ],
    "pages": [
      "223–241"
    ],
    "title": [
      "Quantum Physics: Illusion or Reality"
    ],
    "type": "article-journal"
  },
  {
    "author": [
      {
        "family": "Cohen",
        "given": "David W."
      }
    ],
    "citation-number": [
      "14"
    ],
    "date": [
      "1989"
    ],
    "publisher": [
      "Springer-Verlag"
    ],
    "title": [
      "An Introduction to Hilbert Space and Quantum Logic, 94-104"
    ],
    "type": "book"
  },
  {
    "author": [
      {
        "family": "Boh",
        "given": "N."
      }
    ],
    "citation-number": [
      "15"
    ],
    "container-title": [
      "Physical Review"
    ],
    "date": [
      "1935"
    ],
    "pages": [
      "696"
    ],
    "title": [
      "Can Quantum-Mechanical Description of Physical Reality Be Considered Complete?"
    ],
    "type": "article-journal",
    "volume": [
      "48"
    ]
  },
  {
    "author": [
      {
        "family": "Leibfried",
        "given": "D."
      },
      {
        "family": "Knill",
        "given": "E."
      },
      {
        "family": "Seidelin",
        "given": "S."
      },
      {
        "family": "Britton",
        "given": "J."
      },
      {
        "family": "Blakestad",
        "given": "R.B."
      },
      {
        "family": "Chiaverini",
        "given": "J."
      },
      {
        "family": "Hume",
        "given": "D.B."
      },
      {
        "family": "Itano",
        "given": "W.M."
      },
      {
        "family": "Jost",
        "given": "J.D."
      },
      {
        "family": "Langer",
        "given": "C."
      },
      {
        "family": "Ozeri",
        "given": "R."
      },
      {
        "family": "Reichle",
        "given": "R."
      },
      {
        "family": "Wineland",
        "given": "D.J."
      }
    ],
    "citation-number": [
      "16"
    ],
    "container-title": [
      "Nature"
    ],
    "date": [
      "2005",
      "2005-12-01"
    ],
    "doi": [
      "10.1038/nature04251."
    ],
    "pages": [
      "639–642"
    ],
    "title": [
      "Creation of a six-atom ‘Schrödinger cat’ state",
      "|"
    ],
    "type": "article-journal",
    "volume": [
      "438"
    ]
  },
  {
    "author": [
      {
        "family": "Häffner",
        "given": "H."
      },
      {
        "family": "Hänsel",
        "given": "W."
      },
      {
        "family": "Roos",
        "given": "C.F."
      },
      {
        "family": "Benhelm",
        "given": "J."
      },
      {
        "family": "Chek-al-kar",
        "given": "D."
      },
      {
        "family": "Chwalla",
        "given": "M."
      },
      {
        "family": "Körber",
        "given": "T."
      },
      {
        "family": "Rapol",
        "given": "U.D."
      },
      {
        "family": "Riebe",
        "given": "M."
      },
      {
        "family": "Schmidt",
        "given": "P.O."
      },
      {
        "family": "Becher",
        "given": "C."
      },
      {
        "family": "Gühne",
        "given": "O."
      },
      {
        "family": "Dür",
        "given": "W."
      },
      {
        "family": "Blatt",
        "given": "R."
      }
    ],
    "citation-number": [
      "17"
    ],
    "container-title": [
      "Nature"
    ],
    "date": [
      "2005",
      "2005-12-01"
    ],
    "doi": [
      "10.1038/nature04279."
    ],
    "pages": [
      "643–646"
    ],
    "title": [
      "Scalable multi-particle entanglement of trapped ions",
      "|"
    ],
    "type": "article-journal",
    "volume": [
      "438"
    ]
  },
  {
    "author": [
      {
        "family": "Wang",
        "given": "Yi-Tao"
      },
      {
        "family": "Tang",
        "given": "Jian-Shun"
      },
      {
        "family": "Wei",
        "given": "Zhi-Yuan"
      },
      {
        "family": "Yu",
        "given": "Shang"
      }
    ],
    "citation-number": [
      "18"
    ],
    "container-title": [
      "Phys. Rev. Lett"
    ],
    "date": [
      "2017"
    ],
    "note": [
      "Published 12 January, 2017."
    ],
    "pages": [
      "020403"
    ],
    "title": [
      "Zhi-Jin 94 Chapter One Ke, Xiao-Ye Xu, Chuan-Feng Li, and Guang-Can Guo",
      "Directly Measuring the Degree of Quantum Coherence using Interference Fringes"
    ],
    "type": "article-journal",
    "volume": [
      "118"
    ]
  },
  {
    "author": [
      {
        "family": "Hensen",
        "given": "B."
      },
      {
        "family": "Bernien",
        "given": "H."
      },
      {
        "family": "Dréau",
        "given": "A.E."
      },
      {
        "family": "Reiserer",
        "given": "A."
      },
      {
        "family": "Kalb",
        "given": "N."
      },
      {
        "family": "Blok",
        "given": "M.S."
      },
      {
        "family": "Ruitenberg",
        "given": "J."
      },
      {
        "family": "Vermeulen",
        "given": "R.F.L."
      },
      {
        "family": "Schouten",
        "given": "R.N."
      },
      {
        "family": "Abellán",
        "given": "C."
      },
      {
        "family": "Amaya",
        "given": "W."
      },
      {
        "family": "Pruneri",
        "given": "V."
      },
      {
        "family": "Mitchell",
        "given": "M.W."
      },
      {
        "family": "Markham",
        "given": "M."
      },
      {
        "family": "Twitchen",
        "given": "D.J."
      },
      {
        "family": "Elkouss",
        "given": "D."
      },
      {
        "family": "Wehner",
        "given": "S."
      },
      {
        "family": "Taminiau",
        "given": "T.H."
      },
      {
        "family": "Hanson",
        "given": "R."
      }
    ],
    "citation-number": [
      "19"
    ],
    "container-title": [
      "Nature"
    ],
    "date": [
      "2015"
    ],
    "pages": [
      "682–686"
    ],
    "title": [
      "Loophole-free Bell inequality violation using electron spins separated by 1.3 kilometres"
    ],
    "type": "article-journal",
    "volume": [
      "526"
    ]
  },
  {
    "author": [
      {
        "family": "Schrödinger",
        "given": "E."
      }
    ],
    "citation-number": [
      "20"
    ],
    "container-title": [
      "Cambridge. Phil. Sol"
    ],
    "date": [
      "1935"
    ],
    "pages": [
      "555–763"
    ],
    "title": [
      "Proc"
    ],
    "type": "article-journal",
    "volume": [
      "31"
    ]
  },
  {
    "author": [
      {
        "family": "Neumann",
        "given": "J.",
        "particle": "Von"
      }
    ],
    "citation-number": [
      "21"
    ],
    "date": [
      "1955",
      "1932"
    ],
    "location": [
      "Princeton"
    ],
    "publisher": [
      "Princeton University Press. German Version"
    ],
    "title": [
      "Mathematical Foundations of Quantum Mechanics"
    ],
    "type": "book"
  },
  {
    "author": [
      {
        "family": "Bell",
        "given": "J."
      }
    ],
    "citation-number": [
      "22"
    ],
    "container-title": [
      "Physics",
      "Rev. Mod. Phys"
    ],
    "date": [
      "1964",
      "1966"
    ],
    "pages": [
      "195–200",
      "447"
    ],
    "type": "article-journal",
    "volume": [
      "1",
      "38"
    ]
  },
  {
    "author": [
      {
        "family": "Aspect",
        "given": "A."
      },
      {
        "others": true
      }
    ],
    "citation-number": [
      "23"
    ],
    "container-title": [
      "Phys. Rev. Letts",
      "ibid"
    ],
    "date": [
      "1981",
      "1982",
      "1982"
    ],
    "pages": [
      "460",
      "191",
      "1804"
    ],
    "type": "article-journal",
    "volume": [
      "47",
      "ibid. 48",
      "49"
    ]
  },
  {
    "author": [
      {
        "family": "Kasday",
        "given": "L.R."
      },
      {
        "family": "Ulman",
        "given": "J.D."
      },
      {
        "family": "Wu",
        "given": "C.S."
      }
    ],
    "citation-number": [
      "24"
    ],
    "container-title": [
      "Nuovo Cimento"
    ],
    "date": [
      "1957"
    ],
    "pages": [
      "633"
    ],
    "type": "article-journal",
    "volume": [
      "25B"
    ]
  },
  {
    "author": [
      {
        "family": "Tu",
        "given": "Runsheng"
      }
    ],
    "citation-number": [
      "25"
    ],
    "container-title": [
      "Infinite Energy"
    ],
    "date": [
      "2013"
    ],
    "issue": [
      "107"
    ],
    "pages": [
      "44–46"
    ],
    "title": [
      "The Formula Whose Shape Is Similar to a Heisenberg Relation Possesses the Double Meanings of Determinism and Indeterminism"
    ],
    "type": "article-journal",
    "url": [
      "http://www.docin.com/p-765650007.html."
    ],
    "volume": []
  },
  {
    "note": [
      "References"
    ],
    "type": null
  },
  {
    "author": [
      {
        "family": "Tu",
        "given": "R."
      }
    ],
    "citation-number": [
      "1"
    ],
    "container-title": [
      "Journal of Modern Physics"
    ],
    "date": [
      "2017"
    ],
    "doi": [
      "10.4236/jmp.2017.88088."
    ],
    "pages": [
      "1398–1469"
    ],
    "type": "article-journal",
    "url": [
      "https://doi.org/10.4236/jmp.2017.88088."
    ],
    "volume": [
      "8"
    ]
  },
  {
    "author": [
      {
        "literal": "Vladimir B. Braginsky,1 Yuri I. Vorontsov,2 Kip S. Thorne3"
      }
    ],
    "citation-number": [
      "2"
    ],
    "container-title": [
      "Science"
    ],
    "date": [
      "1980"
    ],
    "pages": [
      "547–557"
    ],
    "title": [
      "Quantum Nondemolition Measurements"
    ],
    "type": "article-journal",
    "url": [
      "http://science.sciencemag.org/content/209/4456/547."
    ],
    "volume": [
      "209"
    ]
  },
  {
    "author": [
      {
        "family": "Kocsis",
        "given": "S."
      },
      {
        "family": "Steinberg",
        "given": "A.M."
      },
      {
        "others": true
      }
    ],
    "citation-number": [
      "3"
    ],
    "container-title": [
      "Science"
    ],
    "date": [
      "2011"
    ],
    "pages": [
      "1170"
    ],
    "title": [
      "Observing the Average Trajectories of Single Photons in a Two-slit Interferometer"
    ],
    "type": "article-journal",
    "volume": [
      "332"
    ]
  },
  {
    "author": [
      {
        "family": "Mir",
        "given": "R."
      },
      {
        "family": "Steinberg",
        "given": "A.M."
      },
      {
        "others": true
      }
    ],
    "citation-number": [
      "4"
    ],
    "container-title": [
      "J. Phys"
    ],
    "date": [
      "2007"
    ],
    "pages": [
      "287"
    ],
    "title": [
      "New"
    ],
    "type": "article-journal",
    "volume": [
      "9"
    ]
  },
  {
    "author": [
      {
        "family": "Tu",
        "given": "Runsheng"
      }
    ],
    "citation-number": [
      "5"
    ],
    "container-title": [
      "Infinite Energy"
    ],
    "date": [
      "2013"
    ],
    "issue": [
      "107"
    ],
    "pages": [
      "44–46"
    ],
    "title": [
      "The Formula Whose Shape Is Similar to a Heisenberg Relation Possesses the Double Meanings of Determinism and Indeterminism"
    ],
    "type": "article-journal",
    "url": [
      "http://www.docin.com/p-765650007.html."
    ],
    "volume": []
  },
  {
    "author": [
      {
        "family": "Bell",
        "given": "J.S."
      }
    ],
    "citation-number": [
      "6"
    ],
    "container-title": [
      "Reviews of Modern Physics"
    ],
    "date": [
      "1966"
    ],
    "doi": [
      "10.1103/RevModPhys.38.447."
    ],
    "pages": [
      "447"
    ],
    "title": [
      "On the Problem of Hidden Variables in Quantum Mechanics"
    ],
    "type": "article-journal",
    "url": [
      "https://doi.org/10.1103/RevModPhys.38.447."
    ],
    "volume": [
      "38"
    ]
  },
  {
    "author": [
      {
        "family": "Zuoxiu",
        "given": "He"
      }
    ],
    "citation-number": [
      "7"
    ],
    "container-title": [
      "Studies in Dialectics of Nature"
    ],
    "date": [
      "1989"
    ],
    "issue": [
      "1"
    ],
    "pages": [
      "8–18"
    ],
    "title": [
      "Must the Measurement of Quantum Mechanics be \"Subjective Intervention\"? (Part one"
    ],
    "type": "article-journal",
    "volume": [
      "5"
    ]
  },
  {
    "author": [
      {
        "family": "Zuoxiu",
        "given": "He"
      }
    ],
    "citation-number": [
      "8"
    ],
    "container-title": [
      "Studies in Dialectic of Nature"
    ],
    "date": [
      "1989"
    ],
    "issue": [
      "2"
    ],
    "pages": [
      "1–12 75"
    ],
    "title": [
      "Must the Measurement of Quantum Mechanics be \"Subjective Intervention\"? (Part two"
    ],
    "type": "article-journal",
    "volume": [
      "5"
    ]
  },
  {
    "author": [
      {
        "family": "Neumann",
        "particle": "von"
      }
    ],
    "citation-number": [
      "9"
    ],
    "container-title": [
      "VI. Princeton"
    ],
    "date": [
      "1955"
    ],
    "title": [
      "Mathematical Foundation of Quantum Mechanics, Chap"
    ],
    "type": "article-journal",
    "volume": [
      "N. J"
    ]
  },
  {
    "author": [
      {
        "family": "Tu",
        "given": "Runsheng"
      }
    ],
    "citation-number": [
      "10"
    ],
    "date": [
      "2015"
    ],
    "location": [
      "Lanham"
    ],
    "publisher": [
      "American Academic Press"
    ],
    "title": [
      "Local Realism Quantum Mechanics, 1-292"
    ],
    "type": "book"
  },
  {
    "author": [
      {
        "family": "Tu",
        "given": "Runsheng"
      }
    ],
    "citation-number": [
      "1"
    ],
    "container-title": [
      "Infinite Energy"
    ],
    "date": [
      "2013"
    ],
    "issue": [
      "107"
    ],
    "pages": [
      "44–46"
    ],
    "title": [
      "The Formula Whose Shape Is Similar to a Heisenberg Relation Possesses the Double Meanings of Determinism and Indeterminism"
    ],
    "type": "article-journal",
    "volume": [
      "18"
    ]
  },
  {
    "author": [
      {
        "family": "Tu",
        "given": "Runsheng"
      }
    ],
    "citation-number": [
      "2"
    ],
    "container-title": [
      "South Asian Academic Research Journals"
    ],
    "date": [
      "2013"
    ],
    "issue": [
      "4"
    ],
    "pages": [
      "12–24"
    ],
    "title": [
      "Using an Extranuclear Electron as a Large-scale Elastic Ring, the Results Are Very Interesting"
    ],
    "type": "article-journal",
    "volume": [
      "3"
    ]
  },
  {
    "author": [
      {
        "family": "Wilson",
        "given": "C.M."
      },
      {
        "others": true
      }
    ],
    "citation-number": [
      "3"
    ],
    "date": [
      "2011-05-24"
    ],
    "note": [
      "Preprint at"
    ],
    "publisher": [
      "Cornell University Library"
    ],
    "title": [
      "Observation of the Dynamical Casimir Effect in a Superconducting Circuit"
    ],
    "type": null,
    "url": [
      "http://arxiv.org/abs/1105.4714."
    ]
  },
  {
    "author": [
      {
        "family": "Guangjing",
        "given": "Ni"
      },
      {
        "family": "Suqing",
        "given": "Cheng"
      }
    ],
    "citation-number": [
      "4"
    ],
    "date": [
      "2005"
    ],
    "edition": [
      "Third"
    ],
    "location": [
      "Shanghai"
    ],
    "publisher": [
      "Fudan University Press (in Chinese"
    ],
    "title": [
      "Advanced Quantum Mechanics"
    ],
    "type": "book"
  },
  {
    "author": [
      {
        "family": "Dürr",
        "given": "S."
      },
      {
        "family": "Nonn",
        "given": "T."
      },
      {
        "family": "Rempe",
        "given": "G."
      }
    ],
    "citation-number": [
      "5"
    ],
    "container-title": [
      "Nature"
    ],
    "date": [
      "1998"
    ],
    "issue": [
      "6697"
    ],
    "pages": [
      "33–37"
    ],
    "title": [
      "Origin of quantum-mechanical complementarity probed by a `which-way' experiment in an atom interferometer"
    ],
    "type": "article-journal",
    "volume": [
      "395"
    ]
  },
  {
    "author": [
      {
        "family": "Brumfiel",
        "given": "Geoff"
      }
    ],
    "citation-number": [
      "6"
    ],
    "container-title": [
      "at The Logic System, Interpretation System and Measurement View 195 of Local Realism Quantum Mechanics",
      "Naturenews"
    ],
    "date": [
      "2011",
      "2011-06-03"
    ],
    "edition": [
      "Preprint"
    ],
    "title": [
      "Moving mirrors make light from nothing"
    ],
    "type": "article-journal",
    "url": [
      "http://www.nature.com/news/2011/110603/full/news.2011.346.html."
    ]
  },
  {
    "author": [
      {
        "family": "Xiaofeng",
        "given": "Pang"
      }
    ],
    "citation-number": [
      "7"
    ],
    "date": [
      "2009"
    ],
    "location": [
      "Beijing"
    ],
    "publisher": [
      "Electronics Industry Press"
    ],
    "title": [
      "Nonlinear Quantum mechanics"
    ],
    "type": "book"
  },
  {
    "author": [
      {
        "family": "Fei",
        "given": "Shao-Ming"
      },
      {
        "family": "Albeverio",
        "given": "Sergio"
      },
      {
        "family": "Cabello",
        "given": "Adan"
      },
      {
        "family": "Jing",
        "given": "Naihuan"
      },
      {
        "family": "Goswami",
        "given": "Debashish"
      }
    ],
    "citation-number": [
      "8"
    ],
    "container-title": [
      "Advances in Mathematical Physics"
    ],
    "date": [
      "2010"
    ],
    "note": [
      "Special Issue."
    ],
    "title": [
      "Quantum Information and Entanglement"
    ],
    "type": "article-journal"
  },
  {
    "author": [
      {
        "family": "Changpu",
        "given": "Sun"
      }
    ],
    "citation-number": [
      "9"
    ],
    "date": [
      "2006",
      "2009"
    ],
    "note": [
      "Preprint at",
      "in Chinese)."
    ],
    "title": [
      "Quantum Mechanics Survey Question and Quantum Information"
    ],
    "type": null,
    "url": [
      "http://www.vtimes.net/bbs/dispost.asp?boardid=10&postid=184,",
      "http://blog.sciencenet.cn/home.php?mod=space&uid=212815&do="
    ]
  },
  {
    "author": [
      {
        "family": "Guowen",
        "given": "Wang"
      }
    ],
    "citation-number": [
      "10"
    ],
    "date": [
      "2009"
    ],
    "note": [
      "Preprint at"
    ],
    "title": [
      "The error and disaster of wave function collapsing supposition"
    ],
    "type": null,
    "url": [
      "http://blog.sciencenet.cn/home.php?mod=space&uid=212815&do="
    ]
  },
  {
    "author": [
      {
        "family": "Changpu",
        "given": "Sun"
      }
    ],
    "citation-number": [
      "11"
    ],
    "container-title": [
      "Physics"
    ],
    "date": [
      "2010"
    ],
    "issue": [
      "5"
    ],
    "note": [
      "Preprint at",
      "in Chinese)."
    ],
    "pages": [
      "310–321"
    ],
    "title": [
      "New Progress of Foundational Aspects in Quantum Mechanics"
    ],
    "type": "article-journal",
    "url": [
      "http://www.docin.com/p-185206150.html"
    ],
    "volume": [
      "30"
    ]
  },
  {
    "author": [
      {
        "family": "Tianrong",
        "given": "Tan"
      }
    ],
    "citation-number": [
      "12"
    ],
    "container-title": [
      "Journal of Wugang Workers’ College"
    ],
    "date": [
      "1995"
    ],
    "issue": [
      "4"
    ],
    "note": [
      "in Chinese)."
    ],
    "pages": [
      "61–69"
    ],
    "title": [
      "Quantum mechanics realism really didn't lose"
    ],
    "type": "article-journal",
    "volume": [
      "7"
    ]
  },
  {
    "author": [
      {
        "family": "Hailin",
        "given": "Zhou"
      }
    ],
    "citation-number": [
      "13"
    ],
    "container-title": [
      "Nuclear Fusion and Plasma Physics"
    ],
    "date": [
      "1998"
    ],
    "issue": [
      "1"
    ],
    "pages": [
      "11–16"
    ],
    "title": [
      "Binding Force in Wave-particle Interaction [J"
    ],
    "type": "article-journal",
    "volume": [
      "18"
    ]
  },
  {
    "author": [
      {
        "family": "Tu",
        "given": "Runsheng"
      }
    ],
    "citation-number": [
      "14"
    ],
    "container-title": [
      "Journal of Shandong Normal University"
    ],
    "date": [
      "2000"
    ],
    "issue": [
      "1"
    ],
    "note": [
      "in Chinese)."
    ],
    "pages": [
      "31–33"
    ],
    "title": [
      "One kind of plan to beautify quantum mechanics"
    ],
    "type": "article-journal",
    "volume": [
      "15"
    ]
  },
  {
    "author": [
      {
        "family": "Tu",
        "given": "Runsheng"
      }
    ],
    "citation-number": [
      "15"
    ],
    "container-title": [
      "Journal of Ningsia Institute of Technology (Natural Science"
    ],
    "date": [
      "1998"
    ],
    "issue": [
      "1"
    ],
    "note": [
      "in Chinese)."
    ],
    "pages": [
      "117–123"
    ],
    "title": [
      "A concise description way of quantum mechanics"
    ],
    "type": "article-journal",
    "volume": [
      "10"
    ]
  },
  {
    "author": [
      {
        "family": "Dirac",
        "given": "P.A.M."
      }
    ],
    "citation-number": [
      "16"
    ],
    "date": [
      "1978"
    ],
    "location": [
      "New York"
    ],
    "publisher": [
      "John Wiley"
    ],
    "title": [
      "Direction in Physics"
    ],
    "type": "book"
  },
  {
    "author": [
      {
        "family": "Wang",
        "given": "L.J."
      },
      {
        "family": "Kuzmich",
        "given": "A."
      },
      {
        "family": "Dogariu",
        "given": "A."
      }
    ],
    "citation-number": [
      "17"
    ],
    "container-title": [
      "Nature"
    ],
    "date": [
      "2000"
    ],
    "pages": [
      "277–279"
    ],
    "title": [
      "Gain-assisted superluminal light propagation"
    ],
    "type": "article-journal",
    "volume": [
      "406"
    ]
  },
  {
    "note": [
      "References"
    ],
    "type": null
  },
  {
    "author": [
      {
        "family": "Tu",
        "given": "Runsheng"
      }
    ],
    "citation-number": [
      "1]."
    ],
    "container-title": [
      "Int. J. Modern Theo. Physics"
    ],
    "date": [
      "2013"
    ],
    "pages": [
      "118–152"
    ],
    "title": [
      "Trying to Establish Local Realism Quantum Mechanics"
    ],
    "type": "article-journal",
    "url": [
      "http://www.modernscientificpress.com/journals/IJMTP.aspx."
    ],
    "volume": [
      "3"
    ]
  },
  {
    "author": [
      {
        "family": "Tu",
        "given": "Runsheng"
      }
    ],
    "citation-number": [
      "2]."
    ],
    "container-title": [
      "Infinite Energy"
    ],
    "date": [
      "2013"
    ],
    "pages": [
      "44–46"
    ],
    "title": [
      "The Formula Whose Shape Is Similar to a Heisenberg Relation Possesses the Double Meanings of Determinism and Indeterminism"
    ],
    "type": "article-journal",
    "volume": [
      "107"
    ]
  },
  {
    "author": [
      {
        "family": "Tu",
        "given": "Runsheng"
      }
    ],
    "citation-number": [
      "3]."
    ],
    "container-title": [
      "The Successful Applications for Local Realism Quantum Mechanics 213",
      "Journal of Shandong Normal University (Natural Science Edition"
    ],
    "date": [
      "1999"
    ],
    "pages": [
      "64–65"
    ],
    "title": [
      "The uncertainty relation has the determinism and the indeterminism double meaning"
    ],
    "type": "article-journal",
    "volume": [
      "3"
    ]
  },
  {
    "author": [
      {
        "family": "Tu",
        "given": "Runsheng"
      }
    ],
    "citation-number": [
      "4]."
    ],
    "container-title": [
      "Journal of Shandong Normal University"
    ],
    "date": [
      "2000"
    ],
    "pages": [
      "31–33"
    ],
    "title": [
      "One kind of plan to beautify quantum mechanics"
    ],
    "type": "article-journal",
    "volume": [
      "1"
    ]
  },
  {
    "author": [
      {
        "family": "Tu",
        "given": "Runsheng"
      }
    ],
    "citation-number": [
      "5]."
    ],
    "container-title": [
      "Journal of Ningsia Institute of Technology (Nature science"
    ],
    "date": [
      "1998"
    ],
    "pages": [
      "117–123"
    ],
    "title": [
      "A concise description way of quantum mechanics"
    ],
    "type": "article-journal",
    "volume": [
      "1"
    ]
  },
  {
    "author": [
      {
        "family": "Guangjing",
        "given": "N."
      },
      {
        "family": "Suqing",
        "given": "C."
      }
    ],
    "citation-number": [
      "6]."
    ],
    "date": [
      "2005"
    ],
    "location": [
      "Shanghai"
    ],
    "note": [
      "Advanced quantum mechanics (Third Edition) [491"
    ],
    "publisher": [
      "Fudan University Press"
    ],
    "type": null
  },
  {
    "author": [
      {
        "family": "Dürr",
        "given": "S."
      },
      {
        "family": "Nonn",
        "given": "T."
      },
      {
        "family": "Rempe",
        "given": "G."
      }
    ],
    "citation-number": [
      "7]."
    ],
    "container-title": [
      "Nature"
    ],
    "date": [
      "1998"
    ],
    "pages": [
      "33"
    ],
    "type": "article-journal",
    "volume": [
      "395"
    ]
  },
  {
    "author": [
      {
        "family": "Xiaofeng",
        "given": "P."
      }
    ],
    "citation-number": [
      "8]."
    ],
    "date": [
      "2009"
    ],
    "location": [
      "Beijing"
    ],
    "publisher": [
      "Electronics Industry Press"
    ],
    "title": [
      "Nonlinear quantum mechanics [317"
    ],
    "type": "book"
  },
  {
    "author": [
      {
        "family": "Changpu",
        "given": "S."
      }
    ],
    "citation-number": [
      "9]."
    ],
    "date": [
      "2006"
    ],
    "title": [
      "Quantum Mechanics Survey Question and Quantum Information"
    ],
    "type": null,
    "url": [
      "http://www.vtimes.net/bbs/dispost.asp?boardid=10&postid=184."
    ]
  },
  {
    "author": [
      {
        "family": "Guowen",
        "given": "W."
      }
    ],
    "citation-number": [
      "10]."
    ],
    "date": [
      "2009"
    ],
    "title": [
      "The Error and Disaster of Wave Function Collapsing Supposition"
    ],
    "type": null,
    "url": [
      "http://blog.sciencenet.cn/home.php?mod=space&uid=212815&do="
    ]
  },
  {
    "author": [
      {
        "family": "Tianrong",
        "given": "Tang"
      }
    ],
    "citation-number": [
      "11]."
    ],
    "container-title": [
      "Journal of Wugang Workers’ College"
    ],
    "date": [
      "1995"
    ],
    "pages": [
      "61–69"
    ],
    "title": [
      "Quantum Mechanics Realism Really Didn't Lose"
    ],
    "type": "article-journal",
    "volume": [
      "4"
    ]
  },
  {
    "author": [
      {
        "family": "Hailin",
        "given": "Z."
      }
    ],
    "citation-number": [
      "12]."
    ],
    "container-title": [
      "Nuclear Fusion and Plasma Physics"
    ],
    "date": [
      "1998"
    ],
    "pages": [
      "11–16"
    ],
    "title": [
      "Binding Force in Wave-particle Interaction"
    ],
    "type": "article-journal",
    "volume": [
      "1"
    ]
  },
  {
    "author": [
      {
        "family": "Wilson",
        "given": "C.M."
      },
      {
        "others": true
      }
    ],
    "citation-number": [
      "13]."
    ],
    "date": [
      "2011"
    ],
    "title": [
      "Observation of the Dynamical Casimir Effect in a Superconducting Circuit"
    ],
    "type": null,
    "url": [
      "http://arxiv.org/abs/1105.4714."
    ]
  },
  {
    "author": [
      {
        "family": "Youchang",
        "given": "X."
      },
      {
        "family": "Meicheng",
        "given": "S."
      }
    ],
    "citation-number": [
      "14]."
    ],
    "date": [
      "1979"
    ],
    "location": [
      "Beijing"
    ],
    "publisher": [
      "People’s Education Press"
    ],
    "title": [
      "Structure chemistry [47"
    ],
    "type": "book"
  },
  {
    "author": [
      {
        "family": "Lendau",
        "given": "L.D."
      }
    ],
    "citation-number": [
      "15]."
    ],
    "date": [
      "1990"
    ],
    "note": [
      "Fulin, L.] [1-324]."
    ],
    "pages": [
      "231–233"
    ],
    "publisher": [
      "Advanced Education Press"
    ],
    "title": [
      "Quantum mechanics: Theoretical physics concise course"
    ],
    "type": null,
    "volume": [
      "2"
    ]
  },
  {
    "author": [
      {
        "family": "Tu",
        "given": "R."
      }
    ],
    "citation-number": [
      "16]."
    ],
    "container-title": [
      "Int. J. Sci. Rep"
    ],
    "date": [
      "2016"
    ],
    "issue": [
      "8"
    ],
    "pages": [
      "187–200"
    ],
    "title": [
      "The principle and application of experimental method for measuring the interaction energy between electrons in atom"
    ],
    "type": "article-journal",
    "volume": [
      "2"
    ]
  },
  {
    "author": [
      {
        "family": "Tu",
        "given": "R.S."
      }
    ],
    "citation-number": [
      "17"
    ],
    "container-title": [
      "Journal of Modern Physics"
    ],
    "date": [
      "2014"
    ],
    "doi": [
      "10.4236/jmp.2014.56041."
    ],
    "pages": [
      "309–318"
    ],
    "title": [
      "Some Successful Applications for Local-Realism Quantum Mechanics: Nature of Covalent-bond Revealed and Quantitative Analysis of Mechanical Equilibrium for Several Molecules"
    ],
    "type": "article-journal",
    "url": [
      "http://dx.doi.org/10.4236/jmp.2014.56041."
    ],
    "volume": [
      "5"
    ]
  },
  {
    "note": [
      "References"
    ],
    "type": null
  },
  {
    "author": [
      {
        "family": "Dean",
        "given": "John A."
      }
    ],
    "citation-number": [
      "1"
    ],
    "date": [
      "1999"
    ],
    "edition": [
      "15th"
    ],
    "location": [
      "New York"
    ],
    "publisher": [
      "McGraw-Hill, Inc"
    ],
    "title": [
      "Lange’s Handbook of Chemistry, 564-566"
    ],
    "type": "book"
  },
  {
    "author": [
      {
        "family": "Li",
        "given": "Huachang"
      }
    ],
    "citation-number": [
      "2"
    ],
    "date": [
      "2007"
    ],
    "location": [
      "Beijing"
    ],
    "pages": [
      "17–19"
    ],
    "publisher": [
      "Chemical Industry Press"
    ],
    "title": [
      "Practical Handbook of chemistry"
    ],
    "type": "book"
  },
  {
    "author": [
      {
        "family": "Tu",
        "given": "Runsheng"
      }
    ],
    "citation-number": [
      "3"
    ],
    "container-title": [
      "South Asian Academic Research Journals"
    ],
    "date": [
      "2013"
    ],
    "issue": [
      "4"
    ],
    "pages": [
      "12–24"
    ],
    "title": [
      "Using an Extranuclear Electron as a Large-scale Elastic Ring, the Results Are Very Interesting"
    ],
    "type": "article-journal",
    "volume": [
      "3"
    ]
  },
  {
    "author": [
      {
        "family": "Tu",
        "given": "Runsheng"
      }
    ],
    "citation-number": [
      "4"
    ],
    "container-title": [
      "Journal of Modern Physics"
    ],
    "date": [
      "2014"
    ],
    "pages": [
      "309–318"
    ],
    "title": [
      "Some Successful Applications for Local-Realism Quantum Mechanics: Nature of Covalent-bond Revealed and Quantitative Analysis of Mechanical Equilibrium for Several Molecules"
    ],
    "type": "article-journal",
    "volume": [
      "5"
    ]
  },
  {
    "author": [
      {
        "family": "Tu",
        "given": "Runsheng"
      }
    ],
    "citation-number": [
      "5"
    ],
    "date": [
      "2015"
    ],
    "location": [
      "Salt Lake City"
    ],
    "publisher": [
      "American Academic Press"
    ],
    "title": [
      "Local Realism Quantum Mechanics, 1-224"
    ],
    "type": "book"
  },
  {
    "author": [
      {
        "family": "Tu",
        "given": "R.S."
      }
    ],
    "citation-number": [
      "6"
    ],
    "container-title": [
      "Journal of Modern Physics"
    ],
    "date": [
      "2014"
    ],
    "doi": [
      "10.4236/jmp.2014.56041."
    ],
    "pages": [
      "309–318"
    ],
    "title": [
      "Some Successful Applications for Local-Realism Quantum Mechanics: Nature of Covalent-bond Revealed and Quantitative Analysis of Mechanical Equilibrium for Several Molecules"
    ],
    "type": "article-journal",
    "url": [
      "http://dx.doi.org/10.4236/jmp.2014.56041."
    ],
    "volume": [
      "5"
    ]
  },
  {
    "container-title": [
      "The Basic Experiment Design of Local Realism Quantum Mechanics 251"
    ],
    "title": [
      "This experiment is an extension of closed-circuit electron diffraction experiments. This experiment and the electron diffraction experiment in the spark chamber can confirm each other"
    ],
    "type": "chapter"
  },
  {
    "author": [
      {
        "family": "Tu",
        "given": "R.S."
      }
    ],
    "citation-number": [
      "1"
    ],
    "container-title": [
      "Journal of Modern Physics"
    ],
    "date": [
      "2014"
    ],
    "doi": [
      "10.4236/jmp.2014.56041."
    ],
    "pages": [
      "309–318"
    ],
    "title": [
      "Some Successful Applications for Local-Realism Quantum Mechanics: Nature of Covalent-bond Revealed and Quantitative Analysis of Mechanical Equilibrium for Several Molecules"
    ],
    "type": "article-journal",
    "url": [
      "http://dx.doi.org/10.4236/jmp.2014.56041."
    ],
    "volume": [
      "5"
    ]
  },
  {
    "author": [
      {
        "family": "Meili",
        "given": "P.G."
      },
      {
        "family": "Missiroli",
        "given": "G.F."
      },
      {
        "family": "Pozzi",
        "given": "G."
      }
    ],
    "citation-number": [
      "2"
    ],
    "container-title": [
      "American Journal of Physics"
    ],
    "date": [
      "1976"
    ],
    "pages": [
      "306–307"
    ],
    "title": [
      "On the statistical aspect of electron interference phenomena"
    ],
    "type": "article-journal",
    "volume": [
      "44"
    ]
  },
  {
    "author": [
      {
        "family": "Rosa",
        "given": "Rodolfo"
      }
    ],
    "citation-number": [
      "3"
    ],
    "container-title": [
      "Phys. Perspect"
    ],
    "date": [
      "2012"
    ],
    "pages": [
      "178–105"
    ],
    "title": [
      "The Merli-Missiroli-Pozzi two-slit electron-interference experiment"
    ],
    "type": "article-journal",
    "volume": [
      "14"
    ]
  },
  {
    "author": [
      {
        "family": "Kocsis",
        "given": "S."
      },
      {
        "family": "Braverman",
        "given": "B."
      },
      {
        "family": "Ravets",
        "given": "S."
      },
      {
        "family": "Stevens",
        "given": "M.J."
      },
      {
        "family": "Mirin",
        "given": "R.P."
      },
      {
        "family": "Shalm",
        "given": "L.K."
      },
      {
        "family": "Steinberg",
        "given": "A.M."
      }
    ],
    "citation-number": [
      "4"
    ],
    "container-title": [
      "Science"
    ],
    "date": [
      "2011"
    ],
    "pages": [
      "1170–1173"
    ],
    "title": [
      "Observing the Average Trajectories of Single Photons in a Two-Slit Interferometer"
    ],
    "type": "article-journal",
    "volume": [
      "332"
    ]
  },
  {
    "author": [
      {
        "family": "Hensen",
        "given": "B."
      },
      {
        "family": "Bernien",
        "given": "H."
      },
      {
        "family": "Dréau",
        "given": "A.E."
      },
      {
        "family": "Reiserer",
        "given": "A."
      },
      {
        "family": "Kalb",
        "given": "N."
      },
      {
        "family": "Blok",
        "given": "M.S."
      },
      {
        "family": "Ruitenberg",
        "given": "J."
      },
      {
        "family": "Vermeulen",
        "given": "R.F.L."
      },
      {
        "family": "Schouten",
        "given": "R.N."
      },
      {
        "family": "Abellán",
        "given": "C."
      },
      {
        "family": "Amaya",
        "given": "W."
      },
      {
        "family": "Pruneri",
        "given": "V."
      },
      {
        "family": "Mitchell",
        "given": "M.W."
      },
      {
        "family": "Markham",
        "given": "M."
      },
      {
        "family": "Twitchen",
        "given": "D.J."
      },
      {
        "family": "Elkouss",
        "given": "D."
      },
      {
        "family": "Wehner",
        "given": "S."
      },
      {
        "family": "Taminiau",
        "given": "T.H."
      },
      {
        "family": "Hanson",
        "given": "R."
      }
    ],
    "citation-number": [
      "5"
    ],
    "container-title": [
      "Nature"
    ],
    "date": [
      "2015"
    ],
    "pages": [
      "682–686"
    ],
    "title": [
      "Loophole-free Bell inequality violation using electron spins separated by 1.3 kilometres"
    ],
    "type": "article-journal",
    "volume": [
      "526"
    ]
  },
  {
    "citation-number": [
      "1."
    ],
    "note": [
      "↩"
    ],
    "title": [
      "Conditions on sound waves at the closed or open ends of an organ pipe require that either an odd number of quarter wave lengths or an even or an odd number of half wave lengths must just fit into the pipe, which limits the possible notes that can be produced by the pipe. In an atom the wave function must satisfy conditions of continuity and finiteness close to and far from the nucleus, which similarly limit the possible energies of atomic states"
    ],
    "type": null
  },
  {
    "citation-number": [
      "2."
    ],
    "date": [
      "1982"
    ],
    "pages": [
      "443"
    ],
    "publisher": [
      "Oxford University Press"
    ],
    "title": [
      "Quoted by Abraham Pais in “Subtle Is the Lord”: The Science and the Life of Albert Einstein"
    ],
    "type": "book"
  },
  {
    "author": [
      {
        "family": "Feynman",
        "given": "Richard"
      }
    ],
    "citation-number": [
      "3."
    ],
    "date": [
      "1967"
    ],
    "pages": [
      "129"
    ],
    "publisher": [
      "MIT Press"
    ],
    "title": [
      "The Character of Physical Law"
    ],
    "type": "book"
  },
  {
    "author": [
      {
        "family": "Krauss",
        "given": "Lawrence M."
      }
    ],
    "citation-number": [
      "4."
    ],
    "date": [
      "2012"
    ],
    "pages": [
      "138"
    ],
    "publisher": [
      "Free Press"
    ],
    "title": [
      "A Universe from Nothing"
    ],
    "type": "book"
  },
  {
    "author": [
      {
        "family": "Segrè",
        "given": "Gino"
      }
    ],
    "citation-number": [
      "5."
    ],
    "date": [
      "2011"
    ],
    "publisher": [
      "Viking"
    ],
    "title": [
      "Ordinary Geniuses"
    ],
    "type": "book"
  },
  {
    "date": [
      "2016"
    ],
    "publisher": [
      "Dutton"
    ],
    "title": [
      "Carroll in The Big Picture"
    ],
    "type": "book"
  },
  {
    "citation-number": [
      "10."
    ],
    "edition": [
      "second"
    ],
    "note": [
      "Cambridge University Press, 2015)."
    ],
    "title": [
      "I go into this in mathematical detail in Section 3.7 of Lectures on Quantum Mechanics"
    ],
    "type": null
  },
  {
    "author": [
      {
        "family": "Marcelo Gleiser",
        "given": "Quoted",
        "particle": "by"
      }
    ],
    "citation-number": [
      "11."
    ],
    "date": [
      "2014"
    ],
    "pages": [
      "222"
    ],
    "publisher": [
      "Basic Books"
    ],
    "title": [
      "The Island of Knowledge"
    ],
    "type": "book"
  },
  {
    "author": [
      {
        "family": "instance",
        "given": "For"
      }
    ],
    "citation-number": [
      "12."
    ],
    "date": [
      "1995"
    ],
    "note": [
      "and the early “Mirror, Mirror” episode of Star Trek."
    ],
    "publisher": [
      "Scholastic"
    ],
    "title": [
      "Northern Lights by Philip Pullman"
    ],
    "type": null
  },
  {
    "citation-number": [
      "13."
    ],
    "date": [
      "2016-11-10"
    ],
    "title": [
      "Entanglement was recently discussed by Jim Holt in these pages"
    ],
    "type": null
  },
  {
    "citation-number": [
      "14."
    ],
    "title": [
      "This equation is named for Göran Lindblad, but it was also independently discovered by Vittorio Gorini, Andrzej Kossakowski, and George Sudarshan"
    ],
    "type": null
  },
  {
    "citation-number": [
      "15."
    ],
    "container-title": [
      "The New York Review of Books"
    ],
    "date": [
      "2017-01-19"
    ],
    "note": [
      "Issue."
    ],
    "title": [
      "The Trouble with Quantum Mechanics, Steven Weinberg"
    ],
    "type": "article-journal"
  },
  {
    "type": null,
    "url": [
      "http://www.nybooks.com/articles/2017/01/19/trouble-with-quantum-mechanics/."
    ]
  }
]
